airstorm/__init__.py
airstorm/base.py
airstorm/cache.py
airstorm/field_lists.py
airstorm/fields.py
airstorm/functions.py
airstorm/model.py
airstorm/model_list.py
airstorm-0.1.0.dev2.dist-info/LICENSE
airstorm-0.1.0.dev2.dist-info/METADATA
airstorm-0.1.0.dev2.dist-info/WHEEL
airstorm-0.1.0.dev2.dist-info/top_level.txt
airstorm-0.1.0.dev2.dist-info/RECORD
