Metadata-Version: 2.1
Name: airstorm
Version: 0.1.0.dev2
Summary: A Python ORM for Airtable.
Home-page: https://github.com/playsthetic/airstorm
Author: Douglas Lassance
Author-email: douglassance@gmail.com
License: MIT
Platform: UNKNOWN
Requires-Dist: airtable-python-wrapper (~=0.15)
Requires-Dist: inflection (~=0.5)
Provides-Extra: ci
Requires-Dist: flake8-print (~=3.1) ; extra == 'ci'
Requires-Dist: flake8 (~=3.8) ; extra == 'ci'
Requires-Dist: pep8-naming (~=0.11) ; extra == 'ci'
Requires-Dist: pytest-cov (~=2.10.1) ; extra == 'ci'
Requires-Dist: pytest-html (~=2.1.1) ; extra == 'ci'
Requires-Dist: pytest-pep8 (~=1.0.6) ; extra == 'ci'
Requires-Dist: pytest (~=6.1.1) ; extra == 'ci'
Requires-Dist: requests-mock (~=1.8) ; extra == 'ci'
Requires-Dist: sphinx-markdown-tables (~=0.0) ; extra == 'ci'
Requires-Dist: sphinx-rtd-theme (~=0.5) ; extra == 'ci'
Requires-Dist: sphinxcontrib-apidoc (~=0.3) ; extra == 'ci'
Requires-Dist: Sphinx (~=3.2) ; extra == 'ci'
